CHANGELOG.md
fling_client/__init__.py
fling_client/api/__init__.py
fling_client/api/data/__init__.py
fling_client/api/data/add_data_fling_id_add_post.py
fling_client/api/data/add_to_index_index_put.py
fling_client/api/data/get_repo_list_repolist_get.py
fling_client/api/data/read_data_fling_id_get.py
fling_client/api/data/read_index_index_get.py
fling_client/api/default/__init__.py
fling_client/api/default/github_code_callback_get.py
fling_client/api/default/github_login_github_login_get.py
fling_client/api/default/index_get.py
fling_client/api/default/token_to_web_callback_web_prod_get.py
fling_client/api/loophost/__init__.py
fling_client/api/loophost/add_txt_record_txt_record_put.py
fling_client/api/loophost/del_txt_record_txt_record_delete.py
fling_client/api/loophost/expose_app_expose_app_put.py
fling_client/api/names/__init__.py
fling_client/api/names/generate_names_namer_get.py
fling_client/client.py
fling_client/errors.py
fling_client/models/__init__.py
fling_client/models/add_data_fling_id_add_post_response_add_data_fling_id_add_post.py
fling_client/models/add_to_index_index_put_response_add_to_index_index_put.py
fling_client/models/generate_names_namer_get_response_generate_names_namer_get.py
fling_client/models/http_validation_error.py
fling_client/models/read_data_fling_id_get_response_read_data_fling_id_get.py
fling_client/models/read_index_index_get_response_read_index_index_get.py
fling_client/models/validation_error.py
fling_client/py.typed
fling_client/types.py
fling_client-0.1.4.dist-info/METADATA
fling_client-0.1.4.dist-info/WHEEL
fling_client-0.1.4.dist-info/RECORD
