Metadata-Version: 2.1
Name: fling-client
Version: 0.1.4
Summary: A client library for accessing fling
Author: Joshua McKenty
Author-email: jmckenty@gmail.com
Requires-Python: >=3.9,<4.0
Classifier: Programming Language :: Python :: 3
Classifier: Programming Language :: Python :: 3.9
Classifier: Programming Language :: Python :: 3.10
Classifier: Programming Language :: Python :: 3.11
Requires-Dist: attrs (>=21.3.0)
Requires-Dist: httpx (>=0.15.4,<0.24.0)
Requires-Dist: python-dateutil (>=2.8.0,<3.0.0)
